storage_timestamps/__init__.py
storage_timestamps/models.py
storage_timestamps/storage.py
storage_timestamps/management/commands/ts_cleanup.py
storage_timestamps/management/commands/ts_create.py
storage_timestamps/management/commands/ts_dump.py
storage_timestamps/migrations/0001_initial.py
storage_timestamps/migrations/0002_alter_timestamp_id.py
storage_timestamps/migrations/__init__.py
django_storage_timestamps-0.1.1.dist-info/LICENSE
django_storage_timestamps-0.1.1.dist-info/METADATA
django_storage_timestamps-0.1.1.dist-info/WHEEL
django_storage_timestamps-0.1.1.dist-info/top_level.txt
django_storage_timestamps-0.1.1.dist-info/RECORD
