Metadata-Version: 2.1
Name: django-storage-timestamps
Version: 0.1.1
Author: Max-Planck-Gesellschaft
License: MIT
Project-URL: Homepage, https://git.mpib-berlin.mpg.de/castellum/django-storage-timestamps
License-File: LICENSE
Requires-Dist: rfc3161ng
